hypercli_cli/__init__.py
hypercli_cli/billing.py
hypercli_cli/cli.py
hypercli_cli/comfyui.py
hypercli_cli/instances.py
hypercli_cli/jobs.py
hypercli_cli/llm.py
hypercli_cli/output.py
hypercli_cli/renders.py
hypercli_cli/user.py
hypercli_cli/tui/__init__.py
hypercli_cli/tui/job_monitor.py
hypercli_cli-0.4.7.dist-info/METADATA
hypercli_cli-0.4.7.dist-info/WHEEL
hypercli_cli-0.4.7.dist-info/entry_points.txt
hypercli_cli-0.4.7.dist-info/RECORD
