Metadata-Version: 2.4
Name: hypercli-cli
Version: 0.4.7
Summary: CLI for HyperCLI - GPU orchestration and LLM API
Project-URL: Homepage, https://hypercli.com
Project-URL: Documentation, https://docs.hypercli.com
Project-URL: Repository, https://github.com/HyperCLI/hypercli
Author-email: HyperCLI <support@hypercli.com>
License-Expression: MIT
Requires-Python: >=3.10
Requires-Dist: hypercli-sdk[comfyui]>=0.4.3
Requires-Dist: openai>=2.8.1
Requires-Dist: rich>=14.2.0
Requires-Dist: typer>=0.20.0
Requires-Dist: websocket-client>=1.6.0
Provides-Extra: dev
Requires-Dist: pytest>=8.0.0; extra == 'dev'
Requires-Dist: ruff>=0.3.0; extra == 'dev'
